vaillant_plus_cn_api/__init__.py
vaillant_plus_cn_api/api.py
vaillant_plus_cn_api/const.py
vaillant_plus_cn_api/errors.py
vaillant_plus_cn_api/model.py
vaillant_plus_cn_api/websocket.py
vaillant_plus_cn_api-2.0.0.dist-info/LICENSE
vaillant_plus_cn_api-2.0.0.dist-info/METADATA
vaillant_plus_cn_api-2.0.0.dist-info/WHEEL
vaillant_plus_cn_api-2.0.0.dist-info/RECORD
