Metadata-Version: 2.1
Name: vaillant-plus-cn-api
Version: 2.0.0
Summary: Python package for interacting with Vaillant devices sold in China mainland using API
Home-page: https://github.com/daxingplay/vaillant-plus-cn-api
Author: daxingplay
Author-email: daxingplay@gmail.com
Requires-Python: >=3.9
Classifier: Programming Language :: Python :: 3
Classifier: Programming Language :: Python :: 3.9
Classifier: Programming Language :: Python :: 3.10
Classifier: Programming Language :: Python :: 3.11
Requires-Dist: aiohttp (>=3.8.0,<4.0.0)
